beautiful_console/__init__.py
beautiful_console/data.py
beautiful_console/utils.py
beautiful_console-1.0.dist-info/LICENSE
beautiful_console-1.0.dist-info/METADATA
beautiful_console-1.0.dist-info/WHEEL
beautiful_console-1.0.dist-info/top_level.txt
beautiful_console-1.0.dist-info/RECORD
