Metadata-Version: 2.1
Name: beautiful-console
Version: 1.0
Summary: A package for print beautiful logs in console.
Home-page: https://github.com/pourya90091/beautiful-console
Author: pourya90091
Author-email: pourya90091@gmail.com
Project-URL: Bug Tracker, https://github.com/pourya90091/beautiful-console/issues
Classifier: Programming Language :: Python :: 3
Classifier: License :: OSI Approved :: MIT License
Classifier: Operating System :: OS Independent
Requires-Python: >=3.6
License-File: LICENSE
